lineflow/__init__.py
lineflow/helpers.py
lineflow/examples/__init__.py
lineflow/examples/carrier_magazin.py
lineflow/examples/complex_line.py
lineflow/examples/component_assembly.py
lineflow/examples/double_source.py
lineflow/examples/multi_process.py
lineflow/examples/multi_sink.py
lineflow/examples/part_dependence.py
lineflow/examples/showcase_line.py
lineflow/examples/simple_line.py
lineflow/examples/waiting_time.py
lineflow/examples/worker_assignment.py
lineflow/learning/__init__.py
lineflow/learning/curriculum.py
lineflow/learning/helpers.py
lineflow/learning/logger.py
lineflow/learning/rewards.py
lineflow/simulation/__init__.py
lineflow/simulation/connectors.py
lineflow/simulation/environment.py
lineflow/simulation/line.py
lineflow/simulation/movable_objects.py
lineflow/simulation/states.py
lineflow/simulation/stationary_objects.py
lineflow/simulation/stations.py
lineflow/simulation/visualization.py
lineflow_rl-0.2.0.dist-info/licenses/LICENSE
lineflow_rl-0.2.0.dist-info/METADATA
lineflow_rl-0.2.0.dist-info/WHEEL
lineflow_rl-0.2.0.dist-info/top_level.txt
lineflow_rl-0.2.0.dist-info/RECORD
