Metadata-Version: 2.4
Name: lineflow-rl
Version: 0.2.0
Summary: Python tool to simulate assembly lines.
Author-email: Kai Müller <kai.mueller@hs-kempten.de>, Martin Wenzel <martin.wenzel@stud.hs-kempten.de>, Tobias Windisch <tobias.windisch@hs-kempten.de>
Maintainer-email: Tobias Windisch <tobias.windisch@hs-kempten.de>
Requires-Python: <3.14
License-File: LICENSE
Requires-Dist: pandas
Requires-Dist: scipy
Requires-Dist: simpy
Requires-Dist: numpy<2.0.0
Requires-Dist: matplotlib
Requires-Dist: pygame
Requires-Dist: torch
Requires-Dist: wandb
Requires-Dist: tqdm
Requires-Dist: stable_baselines3
Requires-Dist: sb3-contrib
Requires-Dist: gekko
Provides-Extra: dev
Requires-Dist: pytest; extra == "dev"
Requires-Dist: pytest-cov; extra == "dev"
Requires-Dist: mkdocs; extra == "dev"
Requires-Dist: mkdocs-material; extra == "dev"
Requires-Dist: mkdocstrings-python; extra == "dev"
Requires-Dist: mike; extra == "dev"
Requires-Dist: ruff; extra == "dev"
Requires-Dist: debugpy; extra == "dev"
Dynamic: license-file
